pytemp.py
pytemp-0.0.1.dist-info/METADATA
pytemp-0.0.1.dist-info/RECORD
pytemp-0.0.1.dist-info/WHEEL
pytemp-0.0.1.dist-info/top_level.txt
